[
  {
    "key": "moran1950notes",
    "score": 1.0,
    "pubmed": {
      "pmid": "15420245",
      "title": "Notes on continuous stochastic phenomena.",
      "journal": "Biometrika",
      "year": "1950",
      "volume": "37",
      "issue": "1-2",
      "pages": "17-23"
    }
  },
  {
    "key": "haahtela2013biodiversity",
    "score": 1.0,
    "pubmed": {
      "pmid": "23663440",
      "title": "The biodiversity hypothesis and allergic disease: world allergy organization position statement.",
      "journal": "The World Allergy Organization journal",
      "year": "2013",
      "volume": "6",
      "issue": "1",
      "pages": "3"
    }
  },
  {
    "key": "phosri2017interactive",
    "score": 1.0,
    "pubmed": {
      "pmid": "28410518",
      "title": "Interactive effects of specific fine particulate matter compositions and airborne pollen on frequency of clinic visits for pollinosis in Fukuoka, Japan.",
      "journal": "Environmental research",
      "year": "2017",
      "volume": "156",
      "issue": "",
      "pages": "411-419"
    }
  },
  {
    "key": "strachan1989hay",
    "score": 1.0,
    "pubmed": {
      "pmid": "2513902",
      "title": "Hay fever, hygiene, and household size.",
      "journal": "BMJ (Clinical research ed.)",
      "year": "1989",
      "volume": "299",
      "issue": "6710",
      "pages": "1259-60"
    }
  },
  {
    "key": "abe2022tweets",
    "score": 1.0,
    "pubmed": {
      "pmid": "35107434",
      "title": "Exploring Relationships Between Tweet Numbers and Over-the-counter Drug Sales for Allergic Rhinitis: Retrospective Analysis.",
      "journal": "JMIR formative research",
      "year": "2022",
      "volume": "6",
      "issue": "2",
      "pages": "e33941"
    }
  }
]